CHANGES.txt
README.txt
requirements.txt
setup.py
flunc/__init__.py
flunc/blog_cleanup.py
flunc/checkbox.py
flunc/command.py
flunc/fake_form.py
flunc/flunc.py
flunc/logging.py
flunc/monkey.py
flunc/parser.py
flunc/redirect_host.py
flunc/urlinspector.py
flunc/xpath.py
flunc/zope_cleanup.py
flunc/zope_create_doc.py
flunc/zope_get_uid.py
flunc/zope_run_cat_queue.py
flunc.egg-info/PKG-INFO
flunc.egg-info/SOURCES.txt
flunc.egg-info/dependency_links.txt
flunc.egg-info/entry_points.txt
flunc.egg-info/not-zip-safe
flunc.egg-info/requires.txt
flunc.egg-info/top_level.txt