Metadata-Version: 1.0
Name: flunc
Version: 0.6
Summary: Functional test suite runner
Home-page: http://www.coactivate.org/projects/flunc
Author: The Open Planning Project and contributors
Author-email: flunc-dev@lists.coactivate.org
License: GPL
Platform: UNKNOWN
Classifier: Topic :: Software Development :: Testing
Classifier: Topic :: Internet :: WWW/HTTP
Classifier: License :: OSI Approved :: GNU General Public License (GPL)
Classifier: Intended Audience :: Developers
Classifier: Development Status :: 5 - Production/Stable
